<Properties StartupConfiguration="{F8D79369-C1D1-ABC4-4D75-39DE089F0D26}|">
  <MonoDevelop.Ide.Workbench ActiveDocument="Assets/Scripts/SceneLoader.cs">
    <Files>
      <File FileName="Assets/Scripts/SceneLoader.cs" Line="23" Column="25" />
      <File FileName="Assets/Scripts/Gameplay.cs" Line="34" Column="32" />
    </Files>
    <Pads>
      <Pad Id="ProjectPad">
        <State name="__root__">
          <Node name="NumberWizard" expanded="True">
            <Node name="Assets" expanded="True">
              <Node name="Scripts" expanded="True">
                <Node name="SceneLoader.cs" selected="True" />
              </Node>
            </Node>
          </Node>
        </State>
      </Pad>
    </Pads>
  </MonoDevelop.Ide.Workbench>
  <MonoDevelop.Ide.DebuggingService.PinnedWatches />
  <MonoDevelop.Ide.Workspace ActiveConfiguration="Debug" />
  <MonoDevelop.Ide.ItemProperties.Assembly-CSharp PreferredExecutionTarget="8a70dad0-fcec-4102-b937-1308cde678ab" />
  <MonoDevelop.Ide.DebuggingService.Breakpoints>
    <BreakpointStore />
  </MonoDevelop.Ide.DebuggingService.Breakpoints>
  <MultiItemStartupConfigurations />
</Properties>